shortkey/__init__.py
shortkey/res_path.py
shortkey/resources/AppImage.png
shortkey/resources/__init__.py
shortkey/resources/icon.icns
shortkey/resources/icon.png
shortkey/resources/keys.json
shortkey/start.py
shortkey-0.1.0.dist-info/METADATA
shortkey-0.1.0.dist-info/WHEEL
shortkey-0.1.0.dist-info/entry_points.txt
shortkey-0.1.0.dist-info/RECORD
