Metadata-Version: 2.1
Name: shortkey
Version: 0.1.0
Summary: 
Author: David Cho
Author-email: david@cgoods.co.kr
Requires-Python: >=3.8,<3.13
Classifier: Programming Language :: Python :: 3
Classifier: Programming Language :: Python :: 3.8
Classifier: Programming Language :: Python :: 3.9
Classifier: Programming Language :: Python :: 3.10
Classifier: Programming Language :: Python :: 3.11
Classifier: Programming Language :: Python :: 3.12
Requires-Dist: loguru (>=0.7.2,<0.8.0)
Requires-Dist: py2app (>=0.28.6,<0.29.0)
Requires-Dist: pynput (>=1.7.6,<2.0.0)
Requires-Dist: pystray (>=0.19.5,<0.20.0)
